odoo/addons/product_customerinfo_sale/README.rst
odoo/addons/product_customerinfo_sale/__init__.py
odoo/addons/product_customerinfo_sale/__manifest__.py
odoo/addons/product_customerinfo_sale/i18n/ca.po
odoo/addons/product_customerinfo_sale/i18n/de.po
odoo/addons/product_customerinfo_sale/i18n/es.po
odoo/addons/product_customerinfo_sale/i18n/it.po
odoo/addons/product_customerinfo_sale/i18n/nl.po
odoo/addons/product_customerinfo_sale/i18n/product_customerinfo_sale.pot
odoo/addons/product_customerinfo_sale/i18n/product_supplierinfo_for_customer_sale.pot
odoo/addons/product_customerinfo_sale/i18n/pt.po
odoo/addons/product_customerinfo_sale/models/__init__.py
odoo/addons/product_customerinfo_sale/models/sale_order_line.py
odoo/addons/product_customerinfo_sale/readme/CONTRIBUTORS.md
odoo/addons/product_customerinfo_sale/readme/DESCRIPTION.md
odoo/addons/product_customerinfo_sale/readme/ROADMAP.md
odoo/addons/product_customerinfo_sale/readme/USAGE.md
odoo/addons/product_customerinfo_sale/security/ir.model.access.csv
odoo/addons/product_customerinfo_sale/static/description/configuration_customer.png
odoo/addons/product_customerinfo_sale/static/description/description_code.png
odoo/addons/product_customerinfo_sale/static/description/description_code_2.png
odoo/addons/product_customerinfo_sale/static/description/icon.png
odoo/addons/product_customerinfo_sale/static/description/index.html
odoo/addons/product_customerinfo_sale/static/description/search_code.png
odoo/addons/product_customerinfo_sale/static/description/search_code_2.png
odoo/addons/product_customerinfo_sale/tests/__init__.py
odoo/addons/product_customerinfo_sale/tests/test_product_customerinfo_sale.py
odoo/addons/product_customerinfo_sale/views/product_customerinfo_views.xml
odoo/addons/product_customerinfo_sale/views/sale_view.xml
odoo_addon_product_customerinfo_sale-18.0.1.0.1.dist-info/METADATA
odoo_addon_product_customerinfo_sale-18.0.1.0.1.dist-info/WHEEL
odoo_addon_product_customerinfo_sale-18.0.1.0.1.dist-info/top_level.txt
odoo_addon_product_customerinfo_sale-18.0.1.0.1.dist-info/RECORD
