Metadata-Version: 2.1
Name: odoo-addon-product_customerinfo_sale
Version: 18.0.1.0.1
Requires-Python: >=3.10
Requires-Dist: odoo-addon-product_customerinfo==18.0.*
Requires-Dist: odoo==18.0.*
Summary: Loads in every sale order line the customer code defined in the product
Home-page: https://github.com/OCA/sale-workflow
License: AGPL-3
Author: Agile Business Group,Vauxoo,Odoo Community Association (OCA)
Author-email: support@odoo-community.org
Classifier: Programming Language :: Python
Classifier: Framework :: Odoo
Classifier: Framework :: Odoo :: 18.0
Classifier: License :: OSI Approved :: GNU Affero General Public License v3
